{"name": "Global", "value": 1, "children": [{"name": "Global", "value": 1, "children": []}, {"name": "Southeast Asia, East Asia, and Oceania", "value": 1, "children": [{"name": "East Asia", "value": 1, "children": [{"name": "China", "value": 304185629.7}, {"name": "Democratic People's Republic of Korea", "value": 4551591.28}, {"name": "Taiwan (Province of China)", "value": 4050851.72}]}, {"name": "Southeast Asia", "value": 1, "children": [{"name": "Cambodia", "value": 1752042.35}, {"name": "Indonesia", "value": 55597576.92}, {"name": "Lao People's Democratic Republic", "value": 879198.43}, {"name": "Malaysia", "value": 4702968.35}, {"name": "Maldives", "value": 62788.73}, {"name": "Myanmar", "value": 6934721.15}, {"name": "Philippines", "value": 14723781.34}, {"name": "Sri Lanka", "value": 2151612.26}, {"name": "Thailand", "value": 11521663.63}, {"name": "Timor-Leste", "value": 214606.75}, {"name": "Viet Nam", "value": 15991507.35}]}, {"name": "Oceania", "value": 1, "children": [{"name": "Fiji", "value": 141152.59}, {"name": "Kiribati", "value": 21727.74}, {"name": "Marshall Islands", "value": 6928.39}, {"name": "Micronesia (Federated States of)", "value": 22173.58}, {"name": "Papua New Guinea", "value": 1119162.35}, {"name": "Samoa", "value": 24194.86}, {"name": "Solomon Islands", "value": 87099.22}, {"name": "Tonga", "value": 14117.45}, {"name": "Vanuatu", "value": 33330.17}, {"name": "Cook Islands", "value": 2451.84}, {"name": "Guam", "value": 19700.95}, {"name": "Nauru", "value": 1500.56}, {"name": "Niue", "value": 155.6}, {"name": "Northern Mariana Islands", "value": 8830.0}, {"name": "Palau", "value": 2612.89}, {"name": "Tokelau", "value": 166.19}, {"name": "Tuvalu", "value": 1680.54}]}]}, {"name": "Central Europe, Eastern Europe, and Central Asia", "value": 1, "children": [{"name": "Central Asia", "value": 1, "children": [{"name": "Armenia", "value": 671260.7}, {"name": "Azerbaijan", "value": 1581613.08}, {"name": "Georgia", "value": 768969.42}, {"name": "Kazakhstan", "value": 2898767.7}, {"name": "Kyrgyzstan", "value": 824848.94}, {"name": "Mongolia", "value": 539065.56}, {"name": "Tajikistan", "value": 454168.35}, {"name": "Turkmenistan", "value": 514395.23}, {"name": "Uzbekistan", "value": 2544574.54}]}, {"name": "Central Europe", "value": 1, "children": [{"name": "Albania", "value": 535673.75}, {"name": "Bosnia and Herzegovina", "value": 743883.12}, {"name": "Bulgaria", "value": 1341581.4}, {"name": "Croatia", "value": 676752.46}, {"name": "Czechia", "value": 1507144.99}, {"name": "Hungary", "value": 1509044.64}, {"name": "North Macedonia", "value": 425632.14}, {"name": "Montenegro", "value": 105333.26}, {"name": "Poland", "value": 5369025.87}, {"name": "Romania", "value": 3151973.28}, {"name": "Serbia", "value": 1454725.4}, {"name": "Slovakia", "value": 745692.21}, {"name": "Slovenia", "value": 257136.65}]}, {"name": "Eastern Europe", "value": 1, "children": [{"name": "Belarus", "value": 1870811.79}, {"name": "Estonia", "value": 203231.83}, {"name": "Latvia", "value": 389319.46}, {"name": "Lithuania", "value": 467421.68}, {"name": "Republic of Moldova", "value": 659441.05}, {"name": "Russian Federation", "value": 30080689.35}, {"name": "Ukraine", "value": 8781039.16}]}]}, {"name": "High-income", "value": 1, "children": [{"name": "High-income Asia Pacific", "value": 1, "children": [{"name": "Brunei Darussalam", "value": 44856.13}, {"name": "Japan", "value": 19471617.11}, {"name": "Republic of Korea", "value": 9426484.3}, {"name": "Singapore", "value": 560246.55}]}, {"name": "Australasia", "value": 1, "children": [{"name": "Australia", "value": 1623837.57}, {"name": "New Zealand", "value": 325031.37}]}, {"name": "Western Europe", "value": 1, "children": [{"name": "Andorra", "value": 11237.96}, {"name": "Austria", "value": 1252437.92}, {"name": "Belgium", "value": 1217311.66}, {"name": "Cyprus", "value": 225708.08}, {"name": "Denmark", "value": 569097.59}, {"name": "Finland", "value": 539175.45}, {"name": "France", "value": 8632710.64}, {"name": "Germany", "value": 10268056.48}, {"name": "Greece", "value": 2114376.9}, {"name": "Iceland", "value": 21998.67}, {"name": "Ireland", "value": 461914.36}, {"name": "Israel", "value": 793194.73}, {"name": "Italy", "value": 6912048.21}, {"name": "Luxembourg", "value": 58501.75}, {"name": "Malta", "value": 46808.14}, {"name": "Netherlands", "value": 1842805.3}, {"name": "Norway", "value": 443332.07}, {"name": "Portugal", "value": 1411401.36}, {"name": "Spain", "value": 7678506.73}, {"name": "Sweden", "value": 506648.62}, {"name": "Switzerland", "value": 991570.2}, {"name": "United Kingdom", "value": 6639806.16}, {"name": "Greenland", "value": 11271.56}, {"name": "Monaco", "value": 4195.6}, {"name": "San Marino", "value": 2639.28}]}, {"name": "Southern Latin America", "value": 1, "children": [{"name": "Argentina", "value": 4561254.93}, {"name": "Chile", "value": 2459309.13}, {"name": "Uruguay", "value": 389958.8}]}, {"name": "High-income North America", "value": 1, "children": [{"name": "Canada", "value": 2780608.98}, {"name": "United States of America", "value": 27002333.86}]}]}, {"name": "Latin America and Caribbean", "value": 1, "children": [{"name": "Caribbean", "value": 1, "children": [{"name": "Antigua and Barbuda", "value": 3922.34}, {"name": "Bahamas", "value": 15061.4}, {"name": "Barbados", "value": 15532.59}, {"name": "Belize", "value": 24293.01}, {"name": "Cuba", "value": 1689634.12}, {"name": "Dominica", "value": 3867.19}, {"name": "Dominican Republic", "value": 492452.56}, {"name": "Grenada", "value": 7442.86}, {"name": "Guyana", "value": 66126.22}, {"name": "Haiti", "value": 334381.11}, {"name": "Jamaica", "value": 222944.6}, {"name": "Saint Lucia", "value": 13002.58}, {"name": "Saint Vincent and the Grenadines", "value": 8591.93}, {"name": "Suriname", "value": 73520.8}, {"name": "Trinidad and Tobago", "value": 162931.66}]}, {"name": "Andean Latin America", "value": 1, "children": [{"name": "Bolivia (Plurinational State of)", "value": 556729.73}, {"name": "Ecuador", "value": 1427170.66}, {"name": "Peru", "value": 1040102.72}, {"name": "Bermuda", "value": 4886.62}]}, {"name": "Central Latin America", "value": 1, "children": [{"name": "Colombia", "value": 3077085.84}, {"name": "Costa Rica", "value": 287979.78}, {"name": "El Salvador", "value": 321388.92}, {"name": "Guatemala", "value": 990342.89}, {"name": "Honduras", "value": 613285.54}, {"name": "Mexico", "value": 10950449.12}, {"name": "Nicaragua", "value": 418585.5}, {"name": "Panama", "value": 162889.0}, {"name": "Venezuela (Bolivarian Republic of)", "value": 2420854.51}, {"name": "Puerto Rico", "value": 233429.84}, {"name": "Saint Kitts and Nevis", "value": 2475.42}, {"name": "United States Virgin Islands", "value": 3668.15}]}, {"name": "Tropical Latin America", "value": 1, "children": [{"name": "Brazil", "value": 12840510.92}, {"name": "Paraguay", "value": 543425.57}, {"name": "American Samoa", "value": 7854.62}]}]}, {"name": "North Africa and Middle East", "value": 1, "children": []}, {"name": "South Asia", "value": 1, "children": []}, {"name": "Sub-Saharan Africa", "value": 1, "children": [{"name": "Central Sub-Saharan Africa", "value": 1, "children": [{"name": "Angola", "value": 964150.14}, {"name": "Central African Republic", "value": 197754.03}, {"name": "Congo", "value": 268847.66}, {"name": "Democratic Republic of the Congo", "value": 3697679.0}, {"name": "Equatorial Guinea", "value": 76549.34}, {"name": "Gabon", "value": 104268.79}]}, {"name": "Eastern Sub-Saharan Africa", "value": 1, "children": [{"name": "Burundi", "value": 337236.95}, {"name": "Comoros", "value": 46621.42}, {"name": "Djibouti", "value": 129632.79}, {"name": "Eritrea", "value": 198491.67}, {"name": "Ethiopia", "value": 1927274.46}, {"name": "Kenya", "value": 2204474.34}, {"name": "Madagascar", "value": 1621498.07}, {"name": "Malawi", "value": 762877.21}, {"name": "Mauritius", "value": 198180.59}, {"name": "Mozambique", "value": 1276705.44}, {"name": "Rwanda", "value": 499192.18}, {"name": "Seychelles", "value": 15119.76}, {"name": "Somalia", "value": 744442.99}, {"name": "United Republic of Tanzania", "value": 2389894.15}, {"name": "Uganda", "value": 1275228.99}, {"name": "Zambia", "value": 971219.95}, {"name": "South Sudan", "value": 508086.22}, {"name": "Sudan", "value": 2018029.8}]}, {"name": "Southern Sub-Saharan Africa", "value": 1, "children": [{"name": "Botswana", "value": 218986.67}, {"name": "Lesotho", "value": 245540.11}, {"name": "Namibia", "value": 149609.45}, {"name": "South Africa", "value": 6104011.66}, {"name": "Eswatini", "value": 44306.55}, {"name": "Zimbabwe", "value": 1038113.8}]}, {"name": "Western Sub-Saharan Africa", "value": 1, "children": [{"name": "Benin", "value": 263097.44}, {"name": "Burkina Faso", "value": 840633.14}, {"name": "Cameroon", "value": 955097.49}, {"name": "Cabo Verde", "value": 15696.94}, {"name": "Chad", "value": 498900.64}, {"name": "C\u00f4te d'Ivoire", "value": 1668460.87}, {"name": "Gambia", "value": 120072.05}, {"name": "Ghana", "value": 728140.23}, {"name": "Guinea", "value": 778909.32}, {"name": "Guinea-Bissau", "value": 29912.68}, {"name": "Liberia", "value": 156053.0}, {"name": "Mali", "value": 913270.94}, {"name": "Mauritania", "value": 294856.57}, {"name": "Niger", "value": 630142.74}, {"name": "Nigeria", "value": 3839416.58}, {"name": "Sao Tome and Principe", "value": 3556.9}, {"name": "Senegal", "value": 655176.65}, {"name": "Sierra Leone", "value": 551583.41}, {"name": "Togo", "value": 251783.61}]}]}]}