{"name": "Global", "value": 1, "children": [{"name": "Sub-Saharan Africa", "value": 1, "children": [{"name": "Central Sub-Saharan Africa", "value": 1, "children": [{"name": "Angola", "value": 640409.69}, {"name": "Central African Republic", "value": 163066.87}, {"name": "Congo", "value": 112151.0}, {"name": "Democratic Republic of the Congo", "value": 2286736.61}, {"name": "Equatorial Guinea", "value": 31031.77}, {"name": "Gabon", "value": 63726.94}]}, {"name": "Eastern Sub-Saharan Africa", "value": 1, "children": [{"name": "Burundi", "value": 414014.19}, {"name": "Comoros", "value": 35991.95}, {"name": "Djibouti", "value": 53060.56}, {"name": "Eritrea", "value": 129697.59}, {"name": "Ethiopia", "value": 1621256.92}, {"name": "Kenya", "value": 1832374.75}, {"name": "Madagascar", "value": 1446555.44}, {"name": "Malawi", "value": 587121.79}, {"name": "Mauritius", "value": 208613.72}, {"name": "Mozambique", "value": 974768.86}, {"name": "Rwanda", "value": 443428.31}, {"name": "Seychelles", "value": 12887.2}, {"name": "Somalia", "value": 476143.34}, {"name": "United Republic of Tanzania", "value": 1982815.61}, {"name": "Uganda", "value": 916228.09}, {"name": "Zambia", "value": 560718.17}, {"name": "South Sudan", "value": 443904.43}, {"name": "Sudan", "value": 1340049.52}]}, {"name": "Southern Sub-Saharan Africa", "value": 1, "children": [{"name": "Botswana", "value": 163486.81}, {"name": "Lesotho", "value": 165195.93}, {"name": "Namibia", "value": 160603.38}, {"name": "South Africa", "value": 7335131.56}, {"name": "Eswatini", "value": 46631.59}, {"name": "Zimbabwe", "value": 850261.55}]}, {"name": "Western Sub-Saharan Africa", "value": 1, "children": [{"name": "Benin", "value": 226817.96}, {"name": "Burkina Faso", "value": 584717.59}, {"name": "Cameroon", "value": 621036.6}, {"name": "Cabo Verde", "value": 17943.63}, {"name": "Chad", "value": 390044.7}, {"name": "C\u00f4te d'Ivoire", "value": 824419.56}, {"name": "Gambia", "value": 95137.98}, {"name": "Ghana", "value": 487697.37}, {"name": "Guinea", "value": 532668.94}, {"name": "Guinea-Bissau", "value": 20137.41}, {"name": "Liberia", "value": 90704.97}, {"name": "Mali", "value": 413558.54}, {"name": "Mauritania", "value": 277442.3}, {"name": "Niger", "value": 301303.03}, {"name": "Nigeria", "value": 3741352.88}, {"name": "Sao Tome and Principe", "value": 2128.36}, {"name": "Senegal", "value": 645140.98}, {"name": "Sierra Leone", "value": 458878.79}, {"name": "Togo", "value": 226964.92}]}]}]}